gritflag_text_writer/__init__.py
gritflag_text_writer/server.py
gritflag_text_writer-0.1.0.dist-info/METADATA
gritflag_text_writer-0.1.0.dist-info/WHEEL
gritflag_text_writer-0.1.0.dist-info/entry_points.txt
gritflag_text_writer-0.1.0.dist-info/RECORD
